cubes/__init__.py
cubes/nbt.py
cubes/net/__init__.py
cubes/net/connection.py
cubes/net/packetflow.py
cubes/net/serializers/__init__.py
cubes/net/serializers/_abc.py
cubes/net/serializers/_mixins.py
cubes/net/serializers/_nbt.py
cubes/net/serializers/_position.py
cubes/net/serializers/_simple.py
cubes/net/serializers/_string.py
cubes/net/serializers/_uuid.py
cubes/net/serializers/_var_length.py
cubes/net/server.py
cubes/utils.py
pycubes-0.4.2.dist-info/METADATA
pycubes-0.4.2.dist-info/WHEEL
pycubes-0.4.2.dist-info/licenses/LICENSE
pycubes-0.4.2.dist-info/RECORD
