Metadata-Version: 2.1
Name: pyCubes
Version: 0.4.2
Summary: Library for creating servers and clients for Minecraft Java Edition
Home-page: https://github.com/DavisDmitry/pyCubes
Author-Email: DmitryDavis <dmitrydavis@protonmail.com>, Dmitry Davis <dmitrydavis@protonmail.com>
License: MIT
Classifier: Intended Audience :: Developers
Classifier: Intended Audience :: System Administrators
Classifier: License :: OSI Approved :: MIT License
Classifier: Operating System :: OS Independent
Classifier: Programming Language :: Python
Classifier: Programming Language :: Python :: 3
Classifier: Programming Language :: Python :: 3 :: Only
Classifier: Programming Language :: Python :: 3.10
Classifier: Programming Language :: Python :: 3.11
Classifier: Programming Language :: Python :: 3.12
Classifier: Programming Language :: Python :: Implementation :: CPython
Classifier: Topic :: Internet
Classifier: Topic :: Software Development
Classifier: Topic :: Software Development :: Libraries
Classifier: Topic :: Software Development :: Libraries :: Application Frameworks
Classifier: Topic :: Software Development :: Libraries :: Python Modules
Classifier: Typing :: Typed
Project-URL: Homepage, https://github.com/DavisDmitry/pyCubes
Project-URL: Documentation, https://pycubes.dmitrydavis.xyz
Requires-Python: <4.0,>=3.10
Requires-Dist: anyio>=4.3.0
Requires-Dist: nbtlib>=2.0.4
